Metadata-Version: 2.1
Name: diana-2
Version: 0.1
Summary: This is the Python implementation of DIANA Clustering Algorithm
Home-page: UNKNOWN
Author: HPC-ML
Author-email: flcus@example.com
License: MIT
Platform: UNKNOWN
License-File: LICENSE
